desbrava_accounts/__init__.py
desbrava_accounts/api/__init__.py
desbrava_accounts/api/api_v1/__init__.py
desbrava_accounts/api/api_v1/api.py
desbrava_accounts/api/api_v1/endpoints/__init__.py
desbrava_accounts/api/api_v1/endpoints/accounts.py
desbrava_accounts/api/api_v1/endpoints/address.py
desbrava_accounts/api/api_v1/endpoints/login.py
desbrava_accounts/api/api_v1/endpoints/roles.py
desbrava_accounts/api/api_v1/endpoints/user_roles.py
desbrava_accounts/api/api_v1/endpoints/users.py
desbrava_accounts/api/api_v1/endpoints/utils.py
desbrava_accounts/api/deps.py
desbrava_accounts/celeryworker_pre_start.py
desbrava_accounts/constants/__init__.py
desbrava_accounts/constants/role.py
desbrava_accounts/core/__init__.py
desbrava_accounts/core/celery_app.py
desbrava_accounts/core/config.py
desbrava_accounts/core/security.py
desbrava_accounts/crud/__init__.py
desbrava_accounts/crud/base.py
desbrava_accounts/crud/crud_account.py
desbrava_accounts/crud/crud_address.py
desbrava_accounts/crud/crud_role.py
desbrava_accounts/crud/crud_user.py
desbrava_accounts/crud/crud_user_role.py
desbrava_accounts/db/__init__.py
desbrava_accounts/db/base.py
desbrava_accounts/db/base_class.py
desbrava_accounts/db/init_db.py
desbrava_accounts/db/session.py
desbrava_accounts/email-templates/src/new_account.mjml
desbrava_accounts/email-templates/src/reset_password.mjml
desbrava_accounts/email-templates/src/test_email.mjml
desbrava_accounts/initial_data.py
desbrava_accounts/main.py
desbrava_accounts/models/__init__.py
desbrava_accounts/models/account.py
desbrava_accounts/models/address.py
desbrava_accounts/models/role.py
desbrava_accounts/models/subscription.py
desbrava_accounts/models/user.py
desbrava_accounts/models/user_role.py
desbrava_accounts/schemas/__init__.py
desbrava_accounts/schemas/account.py
desbrava_accounts/schemas/address.py
desbrava_accounts/schemas/item.py
desbrava_accounts/schemas/msg.py
desbrava_accounts/schemas/role.py
desbrava_accounts/schemas/sign_up.py
desbrava_accounts-0.1.0.dist-info/WHEEL
desbrava_accounts-0.1.0.dist-info/METADATA
desbrava_accounts-0.1.0.dist-info/RECORD
